harness_tui/__init__.py
harness_tui/__main__.py
harness_tui/api/__init__.py
harness_tui/api/logs.py
harness_tui/api/mixin.py
harness_tui/api/pipeline.py
harness_tui/app.py
harness_tui/app.tcss
harness_tui/components/__init__.py
harness_tui/components/execution_history.py
harness_tui/components/log_view.py
harness_tui/components/pipeline_list.py
harness_tui/components/yaml_editor.py
harness_tui/models/__init__.py
harness_tui/models/pipeline.py
harness_tui/utils.py
harness_tui/vectordb/__init__.py
harness_tui-0.1.2.dist-info/METADATA
harness_tui-0.1.2.dist-info/WHEEL
harness_tui-0.1.2.dist-info/entry_points.txt
harness_tui-0.1.2.dist-info/RECORD
