Metadata-Version: 2.1
Name: harness-tui
Version: 0.1.2
Summary: A text user interface for managing and interacting with harness.io
Author: z3z1ma
Author-email: butler.alex2010@gmail.com
Requires-Python: >3.9,<3.13
Classifier: Programming Language :: Python :: 3
Classifier: Programming Language :: Python :: 3.10
Classifier: Programming Language :: Python :: 3.11
Classifier: Programming Language :: Python :: 3.12
Requires-Dist: jsonschema (>=4.22.0,<5.0.0)
Requires-Dist: lancedb (>=0.8.0,<0.9.0)
Requires-Dist: langchain (>=0.2.1,<0.3.0)
Requires-Dist: langchain-community (>=0.2.1,<0.3.0)
Requires-Dist: langchain-openai (>=0.1.8,<0.2.0)
Requires-Dist: openai (>=1.30.5,<2.0.0)
Requires-Dist: pandas (>=2.2.2,<3.0.0)
Requires-Dist: pydantic (>=2.7.2,<3.0.0)
Requires-Dist: python-dotenv (>=1.0.1,<2.0.0)
Requires-Dist: pyyaml (>=6.0.1,<7.0.0)
Requires-Dist: sseclient-py (>=1.8.0,<2.0.0)
Requires-Dist: textual[syntax] (>=0.63.5,<0.64.0)
